gee_polygons/__init__.py
gee_polygons/_modidx.py
gee_polygons/charts.py
gee_polygons/collection.py
gee_polygons/core.py
gee_polygons/export.py
gee_polygons/extract.py
gee_polygons/indices.py
gee_polygons/layers.py
gee_polygons/site.py
gee_polygons/visualize.py
gee_polygons/datasets/__init__.py
gee_polygons/datasets/alpha_embeddings.py
gee_polygons/datasets/dynamicworld.py
gee_polygons/datasets/mapbiomas.py
gee_polygons/datasets/sentinel2.py
gee_polygons-0.0.4.dist-info/licenses/LICENSE
gee_polygons-0.0.4.dist-info/METADATA
gee_polygons-0.0.4.dist-info/WHEEL
gee_polygons-0.0.4.dist-info/entry_points.txt
gee_polygons-0.0.4.dist-info/top_level.txt
gee_polygons-0.0.4.dist-info/RECORD
