Metadata-Version: 2.4
Name: gee-polygons
Version: 0.0.4
Summary: A polygon-first Google Earth Engine library for extracting features, tracking changes over time, and preparing data for modeling or analysis.
Home-page: https://github.com/aliceheiman/gee-polygons
Author: aliceheiman
Author-email: aliceheiman <aheiman@stanford.edu>
License: Apache-2.0
Project-URL: Repository, https://github.com/aliceheiman/gee-polygons
Project-URL: Documentation, https://aliceheiman.github.io/gee-polygons
Keywords: nbdev,jupyter,notebook,python
Classifier: Natural Language :: English
Classifier: Intended Audience :: Developers
Classifier: Development Status :: 3 - Alpha
Classifier: Programming Language :: Python :: 3
Classifier: Programming Language :: Python :: 3 :: Only
Requires-Python: >=3.9
License-File: LICENSE
Requires-Dist: geemap
Requires-Dist: pyproj
Requires-Dist: fastcore
Requires-Dist: pandas
Requires-Dist: geopandas
Dynamic: author
Dynamic: home-page
Dynamic: license-file
Dynamic: requires-python
